kiauhoku/__init__.py
kiauhoku/config.py
kiauhoku/stargrid.py
kiauhoku/extensions/__init__.py
kiauhoku/extensions/calc_HZ.py
kiauhoku/utils/__init__.py
kiauhoku/utils/eep.py
kiauhoku/utils/interp.py
kiauhoku/utils/progress_bar.py
kiauhoku-2.1.2.dist-info/licenses/LICENSE
kiauhoku-2.1.2.dist-info/METADATA
kiauhoku-2.1.2.dist-info/WHEEL
kiauhoku-2.1.2.dist-info/top_level.txt
kiauhoku-2.1.2.dist-info/RECORD
