Metadata-Version: 2.4
Name: kiauhoku
Version: 2.1.2
Summary: Utilities for interacting and interpolating stellar evolution models
Home-page: https://github.com/zclaytor/kiauhoku
Author: Zachary R. Claytor
Author-email: zclaytor@stsci.edu
License: MIT
Classifier: Programming Language :: Python :: 3
Classifier: License :: OSI Approved :: MIT License
Classifier: Operating System :: OS Independent
Classifier: Intended Audience :: Science/Research
Classifier: Topic :: Scientific/Engineering :: Astronomy
Requires-Python: >=3
License-File: LICENSE
Requires-Dist: requests
Requires-Dist: tqdm
Requires-Dist: numpy
Requires-Dist: pandas
Requires-Dist: scipy
Requires-Dist: emcee
Requires-Dist: pyarrow
Requires-Dist: numba
Dynamic: author
Dynamic: author-email
Dynamic: classifier
Dynamic: description
Dynamic: description-content-type
Dynamic: home-page
Dynamic: license
Dynamic: license-file
Dynamic: requires-dist
Dynamic: requires-python
Dynamic: summary
